sim_uart2/uartrtx_top.sv
`timescale 1ns / 1ps

module uartrtx_top(
    input wire [15:0] SW,
    input wire clk,
    output wire [7:0] AN,
    output wire CA,
    output wire CB,
    output wire CC,
    output wire CD,
    output wire CE,
    output wire CF,
    output wire CG,
    output wire DP,
    
    input wire UART_TXD_IN,
//    output wire UART_RXD_OUT,
    input wire UART_RTS
//    output wire UART_CTS
);

reg [15:0] ledsel;
reg [7:0] ledval;

reg clk115k;
reg [9:0]cnt115k;

reg [1:0] rxdata;
reg [1:0] rxstate;
reg [2:0] rxcnt;
reg [7:0] rxval[0:3];
reg [7:0] rxv;

reg [7:0] datacnt;
reg drive;

assign AN[0] = ledsel[15:13] == 3'd0 ? 0 : 1;
assign AN[1] = ledsel[15:13] == 3'd1 ? 0 : 1;
assign AN[2] = ledsel[15:13] == 3'd2 ? 0 : 1;
assign AN[3] = ledsel[15:13] == 3'd3 ? 0 : 1;
assign AN[4] = ledsel[15:13] == 3'd4 ? 0 : 1;
assign AN[5] = ledsel[15:13] == 3'd5 ? 0 : 1;
assign AN[6] = ledsel[15:13] == 3'd6 ? 0 : 1;
assign AN[7] = ledsel[15:13] == 3'd7 ? 0 : 1;

assign CA = ledval[7];
assign CB = ledval[6];
assign CC = ledval[5];
assign CD = ledval[4];
assign CE = ledval[3];
assign CF = ledval[2];
assign CG = ledval[1];
assign DP = ledval[0];

assign UART_RTS = SW[15];

initial begin
	ledsel <= 16'b0;
	clk115k <= 1'b0;
	cnt115k <= 10'b0;

    drive <= 1'b0;
	rxstate <= 2'b0;
	rxv <= 8'b0;
	
	datacnt <= 8'b0;
end

//# CLK 100M
always @(posedge clk) begin
	rxdata[0] <= UART_TXD_IN;
	rxdata[1] <= rxdata[0]; 

	if (~drive && rxdata == 2'b10) begin
		cnt115k <= 10'b0;
		clk115k <= 1'b0;
		drive <= 1'b1;
	end else if (drive) begin
		if (rxstate == 2'd0 && rxdata == 2'b11) begin
			drive <= 1'b0;
		end else if (cnt115k == 10'd433) begin
			cnt115k <= 10'b0;
			clk115k <= clk115k + 1'b1;
		end else begin
			cnt115k <= cnt115k + 10'b1;
		end
	end

//## LED
	ledsel <= ledsel + 16'b1;
	if (ledsel == 16'hFFFF) begin
		ledval <= ledenc(rxv[3:0]);
	end else if (ledsel  == 16'h1FFF) begin
		ledval <= ledenc(rxv[7:4]);
	end else if (ledsel  == 16'h3FFF) begin
		ledval <= ledenc(rxval[1][3:0]);
	end else if (ledsel  == 16'h5FFF) begin
		ledval <= ledenc(rxval[1][7:4]);
	end else if (ledsel  == 16'h7FFF) begin
		ledval <= ledenc(rxval[2][3:0]);
	end else if (ledsel  == 16'h9FFF) begin
		ledval <= ledenc(rxval[2][7:4]);
	end else if (ledsel  == 16'hBFFF) begin
		ledval <= ledenc(datacnt[3:0]);
	end else if (ledsel  == 16'hDFFF) begin
		ledval <= ledenc(datacnt[7:4]);
	end
end

//# CLK 115200
always @(posedge clk115k) begin
	//START
	if (rxstate == 2'b0 && ~UART_TXD_IN) begin
		rxval[1] <= rxv;
		rxval[2] <= rxval[1];
		rxval[3] <= rxval[2];
		datacnt <= datacnt + 8'b1;
		rxstate <= 2'b1;
		rxcnt <= 3'b0;
	//VAL
	end else if (rxstate == 2'd1) begin
		rxv[rxcnt] <= UART_TXD_IN;
		if (rxcnt == 3'd7) begin
			rxstate <= 2'd0;
		end else begin
			rxcnt <= rxcnt + 3'b1;
		end
	end
end

function [7:0] ledenc(input [3:0] inp);
begin
    case (inp)
        4'd0: ledenc = 8'b0000_0011;
        4'd1: ledenc = 8'b1001_1111;
        4'd2: ledenc = 8'b0010_0101;
        4'd3: ledenc = 8'b0000_1101;
        4'd4: ledenc = 8'b1001_1001;
        4'd5: ledenc = 8'b0100_1001;
        4'd6: ledenc = 8'b0100_0001;
        4'd7: ledenc = 8'b0001_1011;
        4'd8: ledenc = 8'b0000_0001;
        4'd9: ledenc = 8'b0000_1001;
        4'd10:ledenc = 8'b0001_0001;
        4'd11:ledenc = 8'b1100_0001;
        4'd12:ledenc = 8'b1110_0101;
        4'd13:ledenc = 8'b1000_0101;
        4'd14:ledenc = 8'b0110_0001;
        default: ledenc = 8'b0111_0001;
     endcase
end
endfunction

endmodule

sim_uartpll/rxsim.v
`timescale 1ps/1ps
module rxsim();

  reg clk;
	wire [7:0] leds;
	reg rxdata;

	uartrtx_top ut(
		.clk(clk),
		.SW(16'hFF),
		.UART_TXD_IN(rxdata)
	);

  initial begin
    clk = 0;
    forever #5 clk = ~clk;
  end

 integer i;  
  initial begin
    $dumpfile("rxsim.vcd");
    $dumpvars(0, rxsim);
//    $monitor ("%t: clk = %b", $time, clk);
  end


  initial begin
		rxdata = 1;
		#300 rxdata = 0;
		#8680 rxdata = 1;
		#8681 rxdata = 0;
		#8680 rxdata = 1;
		#100000 rxdata = 0;
		#8680 rxdata = 1;
    #200000 $finish();
  end

endmodule

sim_uart2/rxsim.vcd
$date
	Wed Sep 16 15:44:30 2020
$end
$version
	Icarus Verilog
$end
$timescale
	1ps
$end
$scope module rxsim $end
$var reg 1 ! clk $end
$var reg 1 " rxdata $end
$scope module ut $end
$var wire 16 # SW [15:0] $end
$var wire 1 " UART_TXD_IN $end
$var wire 1 ! clk $end
$var wire 1 $ UART_RTS $end
$var wire 1 % DP $end
$var wire 1 & CG $end
$var wire 1 ' CF $end
$var wire 1 ( CE $end
$var wire 1 ) CD $end
$var wire 1 * CC $end
$var wire 1 + CB $end
$var wire 1 , CA $end
$var wire 8 - AN [7:0] $end
$var reg 1 . clk115k $end
$var reg 10 / cnt115k [9:0] $end
$var reg 8 0 datacnt [7:0] $end
$var reg 1 1 drive $end
$var reg 16 2 ledsel [15:0] $end
$var reg 8 3 ledval [7:0] $end
$var reg 3 4 rxcnt [2:0] $end
$var reg 2 5 rxdata [1:0] $end
$var reg 2 6 rxstate [1:0] $end
$var reg 8 7 rxv [7:0] $end
$scope function ledenc $end
$var reg 4 8 inp [3:0] $end
$var reg 8 9 ledenc [7:0] $end
$upscope $end
$upscope $end
$upscope $end
$enddefinitions $end
#0
$dumpvars
bx 9
bx 8
b0 7
b0 6
bx 5
bx 4
bx 3
b0 2
01
b0 0
b0 /
0.
b11111110 -
x,
x+
x*
x)
x(
x'
x&
x%
0$
b11111111 #
1"
0!
$end
#5
b1 2
bx1 5
1!
#10
0!
#15
b10 2
b11 5
1!
#20
0!
#25
b11 2
1!
#30
0!
#35
b100 2
1!
#40
0!
#45
b101 2
1!
#50
0!
#55
b110 2
1!
#60
0!
#65
b111 2
1!
#70
0!
#75
b1000 2
1!
#80
0!
#85
b1001 2
1!
#90
0!
#95
b1010 2
1!
#100
0!
#105
b1011 2
1!
#110
0!
#115
b1100 2
1!
#120
0!
#125
b1101 2
1!
#130
0!
#135
b1110 2
1!
#140
0!
#145
b1111 2
1!
#150
0!
#155
b10000 2
1!
#160
0!
#165
b10001 2
1!
#170
0!
#175
b10010 2
1!
#180
0!
#185
b10011 2
1!
#190
0!
#195
b10100 2
1!
#200
0!
#205
b10101 2
1!
#210
0!
#215
b10110 2
1!
#220
0!
#225
b10111 2
1!
#230
0!
#235
b11000 2
1!
#240
0!
#245
b11001 2
1!
#250
0!
#255
b11010 2
1!
#260
0!
#265
b11011 2
1!
#270
0!
#275
b11100 2
1!
#280
0!
#285
b11101 2
1!
#290
0!
#295
b11110 2
1!
#300
0!
0"
#305
b11111 2
b10 5
1!
#310
0!
#315
b100000 2
11
b0 5
1!
#320
0!
#325
b100001 2
b1 /
1!
#330
0!
#335
b100010 2
b10 /
1!
#340
0!
#345
b100011 2
b11 /
1!
#350
0!
#355
b100100 2
b100 /
1!
#360
0!
#365
b100101 2
b101 /
1!
#370
0!
#375
b100110 2
b110 /
1!
#380
0!
#385
b100111 2
b111 /
1!
#390
0!
#395
b101000 2
b1000 /
1!
#400
0!
#405
b101001 2
b1001 /
1!
#410
0!
#415
b101010 2
b1010 /
1!
#420
0!
#425
b101011 2
b1011 /
1!
#430
0!
#435
b101100 2
b1100 /
1!
#440
0!
#445
b101101 2
b1101 /
1!
#450
0!
#455
b101110 2
b1110 /
1!
#460
0!
#465
b101111 2
b1111 /
1!
#470
0!
#475
b110000 2
b10000 /
1!
#480
0!
#485
b110001 2
b10001 /
1!
#490
0!
#495
b110010 2
b10010 /
1!
#500
0!
#505
b110011 2
b10011 /
1!
#510
0!
#515
b110100 2
b10100 /
1!
#520
0!
#525
b110101 2
b10101 /
1!
#530
0!
#535
b110110 2
b10110 /
1!
#540
0!
#545
b110111 2
b10111 /
1!
#550
0!
#555
b111000 2
b11000 /
1!
#560
0!
#565
b111001 2
b11001 /
1!
#570
0!
#575
b111010 2
b11010 /
1!
#580
0!
#585
b111011 2
b11011 /
1!
#590
0!
#595
b111100 2
b11100 /
1!
#600
0!
#605
b111101 2
b11101 /
1!
#610
0!
#615
b111110 2
b11110 /
1!
#620
0!
#625
b111111 2
b11111 /
1!
#630
0!
#635
b1000000 2
b100000 /
1!
#640
0!
#645
b1000001 2
b100001 /
1!
#650
0!
#655
b1000010 2
b100010 /
1!
#660
0!
#665
b1000011 2
b100011 /
1!
#670
0!
#675
b1000100 2
b100100 /
1!
#680
0!
#685
b1000101 2
b100101 /
1!
#690
0!
#695
b1000110 2
b100110 /
1!
#700
0!
#705
b1000111 2
b100111 /
1!
#710
0!
#715
b1001000 2
b101000 /
1!
#720
0!
#725
b1001001 2
b101001 /
1!
#730
0!
#735
b1001010 2
b101010 /
1!
#740
0!
#745
b1001011 2
b101011 /
1!
#750
0!
#755
b1001100 2
b101100 /
1!
#760
0!
#765
b1001101 2
b101101 /
1!
#770
0!
#775
b1001110 2
b101110 /
1!
#780
0!
#785
b1001111 2
b101111 /
1!
#790
0!
#795
b1010000 2
b110000 /
1!
#800
0!
#805
b1010001 2
b110001 /
1!
#810
0!
#815
b1010010 2
b110010 /
1!
#820
0!
#825
b1010011 2
b110011 /
1!
#830
0!
#835
b1010100 2
b110100 /
1!
#840
0!
#845
b1010101 2
b110101 /
1!
#850
0!
#855
b1010110 2
b110110 /
1!
#860
0!
#865
b1010111 2
b110111 /
1!
#870
0!
#875
b1011000 2
b111000 /
1!
#880
0!
#885
b1011001 2
b111001 /
1!
#890
0!
#895
b1011010 2
b111010 /
1!
#900
0!
#905
b1011011 2
b111011 /
1!
#910
0!
#915
b1011100 2
b111100 /
1!
#920
0!
#925
b1011101 2
b111101 /
1!
#930
0!
#935
b1011110 2
b111110 /
1!
#940
0!
#945
b1011111 2
b111111 /
1!
#950
0!
#955
b1100000 2
b1000000 /
1!
#960
0!
#965
b1100001 2
b1000001 /
1!
#970
0!
#975
b1100010 2
b1000010 /
1!
#980
0!
#985
b1100011 2
b1000011 /
1!
#990
0!
#995
b1100100 2
b1000100 /
1!
#1000
0!
#1005
b1100101 2
b1000101 /
1!
#1010
0!
#1015
b1100110 2
b1000110 /
1!
#1020
0!
#1025
b1100111 2
b1000111 /
1!
#1030
0!
#1035
b1101000 2
b1001000 /
1!
#1040
0!
#1045
b1101001 2
b1001001 /
1!
#1050
0!
#1055
b1101010 2
b1001010 /
1!
#1060
0!
#1065
b1101011 2
b1001011 /
1!
#1070
0!
#1075
b1101100 2
b1001100 /
1!
#1080
0!
#1085
b1101101 2
b1001101 /
1!
#1090
0!
#1095
b1101110 2
b1001110 /
1!
#1100
0!
#1105
b1101111 2
b1001111 /
1!
#1110
0!
#1115
b1110000 2
b1010000 /
1!
#1120
0!
#1125
b1110001 2
b1010001 /
1!
#1130
0!
#1135
b1110010 2
b1010010 /
1!
#1140
0!
#1145
b1110011 2
b1010011 /
1!
#1150
0!
#1155
b1110100 2
b1010100 /
1!
#1160
0!
#1165
b1110101 2
b1010101 /
1!
#1170
0!
#1175
b1110110 2
b1010110 /
1!
#1180
0!
#1185
b1110111 2
b1010111 /
1!
#1190
0!
#1195
b1111000 2
b1011000 /
1!
#1200
0!
#1205
b1111001 2
b1011001 /
1!
#1210
0!
#1215
b1111010 2
b1011010 /
1!
#1220
0!
#1225
b1111011 2
b1011011 /
1!
#1230
0!
#1235
b1111100 2
b1011100 /
1!
#1240
0!
#1245
b1111101 2
b1011101 /
1!
#1250
0!
#1255
b1111110 2
b1011110 /
1!
#1260
0!
#1265
b1111111 2
b1011111 /
1!
#1270
0!
#1275
b10000000 2
b1100000 /
1!
#1280
0!
#1285
b10000001 2
b1100001 /
1!
#1290
0!
#1295
b10000010 2
b1100010 /
1!
#1300
0!
#1305
b10000011 2
b1100011 /
1!
#1310
0!
#1315
b10000100 2
b1100100 /
1!
#1320
0!
#1325
b10000101 2
b1100101 /
1!
#1330
0!
#1335
b10000110 2
b1100110 /
1!
#1340
0!
#1345
b10000111 2
b1100111 /
1!
#1350
0!
#1355
b10001000 2
b1101000 /
1!
#1360
0!
#1365
b10001001 2
b1101001 /
1!
#1370
0!
#1375
b10001010 2
b1101010 /
1!
#1380
0!
#1385
b10001011 2
b1101011 /
1!
#1390
0!
#1395
b10001100 2
b1101100 /
1!
#1400
0!
#1405
b10001101 2
b1101101 /
1!
#1410
0!
#1415
b10001110 2
b1101110 /
1!
#1420
0!
#1425
b10001111 2
b1101111 /
1!
#1430
0!
#1435
b10010000 2
b1110000 /
1!
#1440
0!
#1445
b10010001 2
b1110001 /
1!
#1450
0!
#1455
b10010010 2
b1110010 /
1!
#1460
0!
#1465
b10010011 2
b1110011 /
1!
#1470
0!
#1475
b10010100 2
b1110100 /
1!
#1480
0!
#1485
b10010101 2
b1110101 /
1!
#1490
0!
#1495
b10010110 2
b1110110 /
1!
#1500
0!
#1505
b10010111 2
b1110111 /
1!
#1510
0!
#1515
b10011000 2
b1111000 /
1!
#1520
0!
#1525
b10011001 2
b1111001 /
1!
#1530
0!
#1535
b10011010 2
b1111010 /
1!
#1540
0!
#1545
b10011011 2
b1111011 /
1!
#1550
0!
#1555
b10011100 2
b1111100 /
1!
#1560
0!
#1565
b10011101 2
b1111101 /
1!
#1570
0!
#1575
b10011110 2
b1111110 /
1!
#1580
0!
#1585
b10011111 2
b1111111 /
1!
#1590
0!
#1595
b10100000 2
b10000000 /
1!
#1600
0!
#1605
b10100001 2
b10000001 /
1!
#1610
0!
#1615
b10100010 2
b10000010 /
1!
#1620
0!
#1625
b10100011 2
b10000011 /
1!
#1630
0!
#1635
b10100100 2
b10000100 /
1!
#1640
0!
#1645
b10100101 2
b10000101 /
1!
#1650
0!
#1655
b10100110 2
b10000110 /
1!
#1660
0!
#1665
b10100111 2
b10000111 /
1!
#1670
0!
#1675
b10101000 2
b10001000 /
1!
#1680
0!
#1685
b10101001 2
b10001001 /
1!
#1690
0!
#1695
b10101010 2
b10001010 /
1!
#1700
0!
#1705
b10101011 2
b10001011 /
1!
#1710
0!
#1715
b10101100 2
b10001100 /
1!
#1720
0!
#1725
b10101101 2
b10001101 /
1!
#1730
0!
#1735
b10101110 2
b10001110 /
1!
#1740
0!
#1745
b10101111 2
b10001111 /
1!
#1750
0!
#1755
b10110000 2
b10010000 /
1!
#1760
0!
#1765
b10110001 2
b10010001 /
1!
#1770
0!
#1775
b10110010 2
b10010010 /
1!
#1780
0!
#1785
b10110011 2
b10010011 /
1!
#1790
0!
#1795
b10110100 2
b10010100 /
1!
#1800
0!
#1805
b10110101 2
b10010101 /
1!
#1810
0!
#1815
b10110110 2
b10010110 /
1!
#1820
0!
#1825
b10110111 2
b10010111 /
1!
#1830
0!
#1835
b10111000 2
b10011000 /
1!
#1840
0!
#1845
b10111001 2
b10011001 /
1!
#1850
0!
#1855
b10111010 2
b10011010 /
1!
#1860
0!
#1865
b10111011 2
b10011011 /
1!
#1870
0!
#1875
b10111100 2
b10011100 /
1!
#1880
0!
#1885
b10111101 2
b10011101 /
1!
#1890
0!
#1895
b10111110 2
b10011110 /
1!
#1900
0!
#1905
b10111111 2
b10011111 /
1!
#1910
0!
#1915
b11000000 2
b10100000 /
1!
#1920
0!
#1925
b11000001 2
b10100001 /
1!
#1930
0!
#1935
b11000010 2
b10100010 /
1!
#1940
0!
#1945
b11000011 2
b10100011 /
1!
#1950
0!
#1955
b11000100 2
b10100100 /
1!
#1960
0!
#1965
b11000101 2
b10100101 /
1!
#1970
0!
#1975
b11000110 2
b10100110 /
1!
#1980
0!
#1985
b11000111 2
b10100111 /
1!
#1990
0!
#1995
b11001000 2
b10101000 /
1!
#2000
0!
#2005
b11001001 2
b10101001 /
1!
#2010
0!
#2015
b11001010 2
b10101010 /
1!
#2020
0!
#2025
b11001011 2
b10101011 /
1!
#2030
0!
#2035
b11001100 2
b10101100 /
1!
#2040
0!
#2045
b11001101 2
b10101101 /
1!
#2050
0!
#2055
b11001110 2
b10101110 /
1!
#2060
0!
#2065
b11001111 2
b10101111 /
1!
#2070
0!
#2075
b11010000 2
b10110000 /
1!
#2080
0!
#2085
b11010001 2
b10110001 /
1!
#2090
0!
#2095
b11010010 2
b10110010 /
1!
#2100
0!
#2105
b11010011 2
b10110011 /
1!
#2110
0!
#2115
b11010100 2
b10110100 /
1!
#2120
0!
#2125
b11010101 2
b10110101 /
1!
#2130
0!
#2135
b11010110 2
b10110110 /
1!
#2140
0!
#2145
b11010111 2
b10110111 /
1!
#2150
0!
#2155
b11011000 2
b10111000 /
1!
#2160
0!
#2165
b11011001 2
b10111001 /
1!
#2170
0!
#2175
b11011010 2
b10111010 /
1!
#2180
0!
#2185
b11011011 2
b10111011 /
1!
#2190
0!
#2195
b11011100 2
b10111100 /
1!
#2200
0!
#2205
b11011101 2
b10111101 /
1!
#2210
0!
#2215
b11011110 2
b10111110 /
1!
#2220
0!
#2225
b11011111 2
b10111111 /
1!
#2230
0!
#2235
b11100000 2
b11000000 /
1!
#2240
0!
#2245
b11100001 2
b11000001 /
1!
#2250
0!
#2255
b11100010 2
b11000010 /
1!
#2260
0!
#2265
b11100011 2
b11000011 /
1!
#2270
0!
#2275
b11100100 2
b11000100 /
1!
#2280
0!
#2285
b11100101 2
b11000101 /
1!
#2290
0!
#2295
b11100110 2
b11000110 /
1!
#2300
0!
#2305
b11100111 2
b11000111 /
1!
#2310
0!
#2315
b11101000 2
b11001000 /
1!
#2320
0!
#2325
b11101001 2
b11001001 /
1!
#2330
0!
#2335
b11101010 2
b11001010 /
1!
#2340
0!
#2345
b11101011 2
b11001011 /
1!
#2350
0!
#2355
b11101100 2
b11001100 /
1!
#2360
0!
#2365
b11101101 2
b11001101 /
1!
#2370
0!
#2375
b11101110 2
b11001110 /
1!
#2380
0!
#2385
b11101111 2
b11001111 /
1!
#2390
0!
#2395
b11110000 2
b11010000 /
1!
#2400
0!
#2405
b11110001 2
b11010001 /
1!
#2410
0!
#2415
b11110010 2
b11010010 /
1!
#2420
0!
#2425
b11110011 2
b11010011 /
1!
#2430
0!
#2435
b11110100 2
b11010100 /
1!
#2440
0!
#2445
b11110101 2
b11010101 /
1!
#2450
0!
#2455
b11110110 2
b11010110 /
1!
#2460
0!
#2465
b11110111 2
b11010111 /
1!
#2470
0!
#2475
b11111000 2
b11011000 /
1!
#2480
0!
#2485
b11111001 2
b11011001 /
1!
#2490
0!
#2495
b11111010 2
b11011010 /
1!
#2500
0!
#2505
b11111011 2
b11011011 /
1!
#2510
0!
#2515
b11111100 2
b11011100 /
1!
#2520
0!
#2525
b11111101 2
b11011101 /
1!
#2530
0!
#2535
b11111110 2
b11011110 /
1!
#2540
0!
#2545
b11111111 2
b11011111 /
1!
#2550
0!
#2555
b100000000 2
b11100000 /
1!
#2560
0!
#2565
b100000001 2
b11100001 /
1!
#2570
0!
#2575
b100000010 2
b11100010 /
1!
#2580
0!
#2585
b100000011 2
b11100011 /
1!
#2590
0!
#2595
b100000100 2
b11100100 /
1!
#2600
0!
#2605
b100000101 2
b11100101 /
1!
#2610
0!
#2615
b100000110 2
b11100110 /
1!
#2620
0!
#2625
b100000111 2
b11100111 /
1!
#2630
0!
#2635
b100001000 2
b11101000 /
1!
#2640
0!
#2645
b100001001 2
b11101001 /
1!
#2650
0!
#2655
b100001010 2
b11101010 /
1!
#2660
0!
#2665
b100001011 2
b11101011 /
1!
#2670
0!
#2675
b100001100 2
b11101100 /
1!
#2680
0!
#2685
b100001101 2
b11101101 /
1!
#2690
0!
#2695
b100001110 2
b11101110 /
1!
#2700
0!
#2705
b100001111 2
b11101111 /
1!
#2710
0!
#2715
b100010000 2
b11110000 /
1!
#2720
0!
#2725
b100010001 2
b11110001 /
1!
#2730
0!
#2735
b100010010 2
b11110010 /
1!
#2740
0!
#2745
b100010011 2
b11110011 /
1!
#2750
0!
#2755
b100010100 2
b11110100 /
1!
#2760
0!
#2765
b100010101 2
b11110101 /
1!
#2770
0!
#2775
b100010110 2
b11110110 /
1!
#2780
0!
#2785
b100010111 2
b11110111 /
1!
#2790
0!
#2795
b100011000 2
b11111000 /
1!
#2800
0!
#2805
b100011001 2
b11111001 /
1!
#2810
0!
#2815
b100011010 2
b11111010 /
1!
#2820
0!
#2825
b100011011 2
b11111011 /
1!
#2830
0!
#2835
b100011100 2
b11111100 /
1!
#2840
0!
#2845
b100011101 2
b11111101 /
1!
#2850
0!
#2855
b100011110 2
b11111110 /
1!
#2860
0!
#2865
b100011111 2
b11111111 /
1!
#2870
0!
#2875
b100100000 2
b100000000 /
1!
#2880
0!
#2885
b100100001 2
b100000001 /
1!
#2890
0!
#2895
b100100010 2
b100000010 /
1!
#2900
0!
#2905
b100100011 2
b100000011 /
1!
#2910
0!
#2915
b100100100 2
b100000100 /
1!
#2920
0!
#2925
b100100101 2
b100000101 /
1!
#2930
0!
#2935
b100100110 2
b100000110 /
1!
#2940
0!
#2945
b100100111 2
b100000111 /
1!
#2950
0!
#2955
b100101000 2
b100001000 /
1!
#2960
0!
#2965
b100101001 2
b100001001 /
1!
#2970
0!
#2975
b100101010 2
b100001010 /
1!
#2980
0!
#2985
b100101011 2
b100001011 /
1!
#2990
0!
#2995
b100101100 2
b100001100 /
1!
#3000
0!
#3005
b100101101 2
b100001101 /
1!
#3010
0!
#3015
b100101110 2
b100001110 /
1!
#3020
0!
#3025
b100101111 2
b100001111 /
1!
#3030
0!
#3035
b100110000 2
b100010000 /
1!
#3040
0!
#3045
b100110001 2
b100010001 /
1!
#3050
0!
#3055
b100110010 2
b100010010 /
1!
#3060
0!
#3065
b100110011 2
b100010011 /
1!
#3070
0!
#3075
b100110100 2
b100010100 /
1!
#3080
0!
#3085
b100110101 2
b100010101 /
1!
#3090
0!
#3095
b100110110 2
b100010110 /
1!
#3100
0!
#3105
b100110111 2
b100010111 /
1!
#3110
0!
#3115
b100111000 2
b100011000 /
1!
#3120
0!
#3125
b100111001 2
b100011001 /
1!
#3130
0!
#3135
b100111010 2
b100011010 /
1!
#3140
0!
#3145
b100111011 2
b100011011 /
1!
#3150
0!
#3155
b100111100 2
b100011100 /
1!
#3160
0!
#3165
b100111101 2
b100011101 /
1!
#3170
0!
#3175
b100111110 2
b100011110 /
1!
#3180
0!
#3185
b100111111 2
b100011111 /
1!
#3190
0!
#3195
b101000000 2
b100100000 /
1!
#3200
0!
#3205
b101000001 2
b100100001 /
1!
#3210
0!
#3215
b101000010 2
b100100010 /
1!
#3220
0!
#3225
b101000011 2
b100100011 /
1!
#3230
0!
#3235
b101000100 2
b100100100 /
1!
#3240
0!
#3245
b101000101 2
b100100101 /
1!
#3250
0!
#3255
b101000110 2
b100100110 /
1!
#3260
0!
#3265
b101000111 2
b100100111 /
1!
#3270
0!
#3275
b101001000 2
b100101000 /
1!
#3280
0!
#3285
b101001001 2
b100101001 /
1!
#3290
0!
#3295
b101001010 2
b100101010 /
1!
#3300
0!
#3305
b101001011 2
b100101011 /
1!
#3310
0!
#3315
b101001100 2
b100101100 /
1!
#3320
0!
#3325
b101001101 2
b100101101 /
1!
#3330
0!
#3335
b101001110 2
b100101110 /
1!
#3340
0!
#3345
b101001111 2
b100101111 /
1!
#3350
0!
#3355
b101010000 2
b100110000 /
1!
#3360
0!
#3365
b101010001 2
b100110001 /
1!
#3370
0!
#3375
b101010010 2
b100110010 /
1!
#3380
0!
#3385
b101010011 2
b100110011 /
1!
#3390
0!
#3395
b101010100 2
b100110100 /
1!
#3400
0!
#3405
b101010101 2
b100110101 /
1!
#3410
0!
#3415
b101010110 2
b100110110 /
1!
#3420
0!
#3425
b101010111 2
b100110111 /
1!
#3430
0!
#3435
b101011000 2
b100111000 /
1!
#3440
0!
#3445
b101011001 2
b100111001 /
1!
#3450
0!
#3455
b101011010 2
b100111010 /
1!
#3460
0!
#3465
b101011011 2
b100111011 /
1!
#3470
0!
#3475
b101011100 2
b100111100 /
1!
#3480
0!
#3485
b101011101 2
b100111101 /
1!
#3490
0!
#3495
b101011110 2
b100111110 /
1!
#3500
0!
#3505
b101011111 2
b100111111 /
1!
#3510
0!
#3515
b101100000 2
b101000000 /
1!
#3520
0!
#3525
b101100001 2
b101000001 /
1!
#3530
0!
#3535
b101100010 2
b101000010 /
1!
#3540
0!
#3545
b101100011 2
b101000011 /
1!
#3550
0!
#3555
b101100100 2
b101000100 /
1!
#3560
0!
#3565
b101100101 2
b101000101 /
1!
#3570
0!
#3575
b101100110 2
b101000110 /
1!
#3580
0!
#3585
b101100111 2
b101000111 /
1!
#3590
0!
#3595
b101101000 2
b101001000 /
1!
#3600
0!
#3605
b101101001 2
b101001001 /
1!
#3610
0!
#3615
b101101010 2
b101001010 /
1!
#3620
0!
#3625
b101101011 2
b101001011 /
1!
#3630
0!
#3635
b101101100 2
b101001100 /
1!
#3640
0!
#3645
b101101101 2
b101001101 /
1!
#3650
0!
#3655
b101101110 2
b101001110 /
1!
#3660
0!
#3665
b101101111 2
b101001111 /
1!
#3670
0!
#3675
b101110000 2
b101010000 /
1!
#3680
0!
#3685
b101110001 2
b101010001 /
1!
#3690
0!
#3695
b101110010 2
b101010010 /
1!
#3700
0!
#3705
b101110011 2
b101010011 /
1!
#3710
0!
#3715
b101110100 2
b101010100 /
1!
#3720
0!
#3725
b101110101 2
b101010101 /
1!
#3730
0!
#3735
b101110110 2
b101010110 /
1!
#3740
0!
#3745
b101110111 2
b101010111 /
1!
#3750
0!
#3755
b101111000 2
b101011000 /
1!
#3760
0!
#3765
b101111001 2
b101011001 /
1!
#3770
0!
#3775
b101111010 2
b101011010 /
1!
#3780
0!
#3785
b101111011 2
b101011011 /
1!
#3790
0!
#3795
b101111100 2
b101011100 /
1!
#3800
0!
#3805
b101111101 2
b101011101 /
1!
#3810
0!
#3815
b101111110 2
b101011110 /
1!
#3820
0!
#3825
b101111111 2
b101011111 /
1!
#3830
0!
#3835
b110000000 2
b101100000 /
1!
#3840
0!
#3845
b110000001 2
b101100001 /
1!
#3850
0!
#3855
b110000010 2
b101100010 /
1!
#3860
0!
#3865
b110000011 2
b101100011 /
1!
#3870
0!
#3875
b110000100 2
b101100100 /
1!
#3880
0!
#3885
b110000101 2
b101100101 /
1!
#3890
0!
#3895
b110000110 2
b101100110 /
1!
#3900
0!
#3905
b110000111 2
b101100111 /
1!
#3910
0!
#3915
b110001000 2
b101101000 /
1!
#3920
0!
#3925
b110001001 2
b101101001 /
1!
#3930
0!
#3935
b110001010 2
b101101010 /
1!
#3940
0!
#3945
b110001011 2
b101101011 /
1!
#3950
0!
#3955
b110001100 2
b101101100 /
1!
#3960
0!
#3965
b110001101 2
b101101101 /
1!
#3970
0!
#3975
b110001110 2
b101101110 /
1!
#3980
0!
#3985
b110001111 2
b101101111 /
1!
#3990
0!
#3995
b110010000 2
b101110000 /
1!
#4000
0!
#4005
b110010001 2
b101110001 /
1!
#4010
0!
#4015
b110010010 2
b101110010 /
1!
#4020
0!
#4025
b110010011 2
b101110011 /
1!
#4030
0!
#4035
b110010100 2
b101110100 /
1!
#4040
0!
#4045
b110010101 2
b101110101 /
1!
#4050
0!
#4055
b110010110 2
b101110110 /
1!
#4060
0!
#4065
b110010111 2
b101110111 /
1!
#4070
0!
#4075
b110011000 2
b101111000 /
1!
#4080
0!
#4085
b110011001 2
b101111001 /
1!
#4090
0!
#4095
b110011010 2
b101111010 /
1!
#4100
0!
#4105
b110011011 2
b101111011 /
1!
#4110
0!
#4115
b110011100 2
b101111100 /
1!
#4120
0!
#4125
b110011101 2
b101111101 /
1!
#4130
0!
#4135
b110011110 2
b101111110 /
1!
#4140
0!
#4145
b110011111 2
b101111111 /
1!
#4150
0!
#4155
b110100000 2
b110000000 /
1!
#4160
0!
#4165
b110100001 2
b110000001 /
1!
#4170
0!
#4175
b110100010 2
b110000010 /
1!
#4180
0!
#4185
b110100011 2
b110000011 /
1!
#4190
0!
#4195
b110100100 2
b110000100 /
1!
#4200
0!
#4205
b110100101 2
b110000101 /
1!
#4210
0!
#4215
b110100110 2
b110000110 /
1!
#4220
0!
#4225
b110100111 2
b110000111 /
1!
#4230
0!
#4235
b110101000 2
b110001000 /
1!
#4240
0!
#4245
b110101001 2
b110001001 /
1!
#4250
0!
#4255
b110101010 2
b110001010 /
1!
#4260
0!
#4265
b110101011 2
b110001011 /
1!
#4270
0!
#4275
b110101100 2
b110001100 /
1!
#4280
0!
#4285
b110101101 2
b110001101 /
1!
#4290
0!
#4295
b110101110 2
b110001110 /
1!
#4300
0!
#4305
b110101111 2
b110001111 /
1!
#4310
0!
#4315
b110110000 2
b110010000 /
1!
#4320
0!
#4325
b110110001 2
b110010001 /
1!
#4330
0!
#4335
b110110010 2
b110010010 /
1!
#4340
0!
#4345
b110110011 2
b110010011 /
1!
#4350
0!
#4355
b110110100 2
b110010100 /
1!
#4360
0!
#4365
b110110101 2
b110010101 /
1!
#4370
0!
#4375
b110110110 2
b110010110 /
1!
#4380
0!
#4385
b110110111 2
b110010111 /
1!
#4390
0!
#4395
b110111000 2
b110011000 /
1!
#4400
0!
#4405
b110111001 2
b110011001 /
1!
#4410
0!
